{"redirects":[{"fromPath":"/admin","isPermanent":true,"ignoreCase":true,"redirectInBrowser":false,"toPath":"https://www.youtube.com/watch?v=dQw4w9WgXcQ","force":true},{"fromPath":"/projects/*","isPermanent":true,"ignoreCase":true,"redirectInBrowser":false,"toPath":"/art","force":true},{"fromPath":"/blog","isPermanent":true,"ignoreCase":true,"redirectInBrowser":false,"toPath":"/writing/","force":true},{"fromPath":"/blog/*","isPermanent":true,"ignoreCase":true,"redirectInBrowser":false,"toPath":"/writing/","force":true},{"fromPath":"/tags","isPermanent":true,"ignoreCase":true,"redirectInBrowser":false,"toPath":"/writing/","force":true},{"fromPath":"/tags/*","isPermanent":true,"ignoreCase":true,"redirectInBrowser":false,"toPath":"/writing/","force":true},{"fromPath":"/categories/*","isPermanent":true,"ignoreCase":true,"redirectInBrowser":false,"toPath":"/writing/","force":true},{"fromPath":"/privacy","isPermanent":true,"ignoreCase":true,"redirectInBrowser":false,"toPath":"/privacy-policy/","force":true},{"fromPath":"/imprint","isPermanent":true,"ignoreCase":true,"redirectInBrowser":false,"toPath":"/legal-notice/","force":true},{"fromPath":"/contact","isPermanent":true,"ignoreCase":true,"redirectInBrowser":false,"toPath":"/about/","force":true},{"fromPath":"/tags/*","isPermanent":true,"ignoreCase":true,"redirectInBrowser":false,"toPath":"/garden/","force":true},{"fromPath":"/tags/gatsby","isPermanent":true,"ignoreCase":true,"redirectInBrowser":false,"toPath":"/gatsby/","force":true},{"fromPath":"/tags/gatsby-starter","isPermanent":true,"ignoreCase":true,"redirectInBrowser":false,"toPath":"/gatsby/","force":true},{"fromPath":"/tags/gatsby-themes","isPermanent":true,"ignoreCase":true,"redirectInBrowser":false,"toPath":"/gatsby/","force":true},{"fromPath":"/tags/compositing","isPermanent":true,"ignoreCase":true,"redirectInBrowser":false,"toPath":"/design/","force":true},{"fromPath":"/tags/photoshop","isPermanent":true,"ignoreCase":true,"redirectInBrowser":false,"toPath":"/design/","force":true},{"fromPath":"/tags/react","isPermanent":true,"ignoreCase":true,"redirectInBrowser":false,"toPath":"/react/","force":true},{"fromPath":"/tags/figma","isPermanent":true,"ignoreCase":true,"redirectInBrowser":false,"toPath":"/design/","force":true},{"fromPath":"/categories/tutorial","isPermanent":true,"ignoreCase":true,"redirectInBrowser":false,"toPath":"/tutorials/","force":true},{"fromPath":"/categories/freebie","isPermanent":true,"ignoreCase":true,"redirectInBrowser":false,"toPath":"/garden/","force":true},{"fromPath":"/categories/quicktipp","isPermanent":true,"ignoreCase":true,"redirectInBrowser":false,"toPath":"/garden/","force":true},{"fromPath":"/en","isPermanent":true,"ignoreCase":true,"redirectInBrowser":false,"toPath":"/","force":true},{"fromPath":"/en/projects","isPermanent":true,"ignoreCase":true,"redirectInBrowser":false,"toPath":"/art","force":true},{"fromPath":"/en/projects/*","isPermanent":true,"ignoreCase":true,"redirectInBrowser":false,"toPath":"/art","force":true},{"fromPath":"/en/blog/*","isPermanent":true,"ignoreCase":true,"redirectInBrowser":false,"toPath":"/writing/","force":true},{"fromPath":"/en/blog","isPermanent":true,"ignoreCase":true,"redirectInBrowser":false,"toPath":"/writing/","force":true},{"fromPath":"/en/contact","isPermanent":true,"ignoreCase":true,"redirectInBrowser":false,"toPath":"/about/","force":true},{"fromPath":"/en/tags/*","isPermanent":true,"ignoreCase":true,"redirectInBrowser":false,"toPath":"/writing/","force":true},{"fromPath":"/en/categories/*","isPermanent":true,"ignoreCase":true,"redirectInBrowser":false,"toPath":"/writing/","force":true},{"fromPath":"/en/privacy","isPermanent":true,"ignoreCase":true,"redirectInBrowser":false,"toPath":"/privacy-policy/","force":true},{"fromPath":"/en/imprint","isPermanent":true,"ignoreCase":true,"redirectInBrowser":false,"toPath":"/legal-notice/","force":true},{"fromPath":"/en/tags/*","isPermanent":true,"ignoreCase":true,"redirectInBrowser":false,"toPath":"/garden","force":true},{"fromPath":"/en/tags/gatsby","isPermanent":true,"ignoreCase":true,"redirectInBrowser":false,"toPath":"/gatsby","force":true},{"fromPath":"/en/tags/gatsby-starter","isPermanent":true,"ignoreCase":true,"redirectInBrowser":false,"toPath":"/gatsby","force":true},{"fromPath":"/en/tags/gatsby-themes","isPermanent":true,"ignoreCase":true,"redirectInBrowser":false,"toPath":"/gatsby","force":true},{"fromPath":"/en/tags/photoshop","isPermanent":true,"ignoreCase":true,"redirectInBrowser":false,"toPath":"/design","force":true},{"fromPath":"/en/tags/react","isPermanent":true,"ignoreCase":true,"redirectInBrowser":false,"toPath":"/react","force":true},{"fromPath":"/en/tags/type-script","isPermanent":true,"ignoreCase":true,"redirectInBrowser":false,"toPath":"/javascript","force":true},{"fromPath":"/en/categories/tutorial","isPermanent":true,"ignoreCase":true,"redirectInBrowser":false,"toPath":"/tutorials/","force":true},{"fromPath":"/en/categories/freebie","isPermanent":true,"ignoreCase":true,"redirectInBrowser":false,"toPath":"/garden/","force":true},{"fromPath":"/en/categories/quick-tip","isPermanent":true,"ignoreCase":true,"redirectInBrowser":false,"toPath":"/garden/","force":true}],"rewrites":[]}